{ "height":18,
 "layers":[
        {
         "data":[32, 33, 32, 33, 32, 33, 32, 33, 32, 33, 32, 33, 32, 33, 32, 33, 32, 33, 32, 33, 33, 32, 33, 1, 1, 1, 1, 1, 1, 1, 1, 1, 1, 128, 1, 1, 128, 1, 1, 32, 32, 33, 1, 1, 1, 1, 1, 1, 1, 1, 1, 1, 1, 129, 1, 1, 129, 1, 1, 33, 33, 1, 1, 1, 1, 1, 1, 1, 1, 1, 1, 1, 1, 127, 1, 1, 127, 1, 1, 32, 32, 1, 1, 1, 1, 1, 1, 1, 1, 1, 1, 1, 32, 33, 30, 31, 32, 33, 32, 33, 33, 1, 1, 1, 1, 1, 1, 1, 92, 94, 1, 1, 1, 1, 30, 31, 1, 1, 1, 32, 32, 1, 1, 1, 1, 1, 1, 1, 93, 95, 1, 1, 1, 1, 30, 31, 1, 1, 1, 33, 33, 1, 1, 1, 1, 1, 1, 1, 1, 1, 1, 1, 1, 1, 30, 31, 1, 1, 1, 32, 32, 30, 31, 33, 32, 33, 32, 33, 1, 1, 1, 30, 31, 33, 32, 33, 32, 33, 32, 33, 33, 30, 31, 1, 1, 1, 1, 1, 1, 1, 1, 30, 31, 1, 128, 1, 1, 128, 1, 32, 32, 30, 31, 1, 1, 1, 1, 1, 1, 1, 1, 30, 31, 1, 129, 1, 1, 129, 1, 33, 33, 30, 31, 1, 1, 1, 1, 1, 1, 1, 1, 30, 31, 1, 127, 1, 1, 127, 1, 32, 32, 33, 32, 33, 32, 30, 31, 33, 32, 33, 32, 33, 32, 33, 32, 30, 31, 33, 32, 33, 33, 81, 81, 81, 81, 30, 31, 81, 81, 81, 81, 81, 81, 81, 81, 30, 31, 81, 81, 32, 32, 81, 1, 1, 81, 30, 31, 81, 81, 81, 81, 81, 81, 81, 81, 30, 31, 81, 81, 33, 33, 81, 1, 1, 81, 30, 31, 81, 81, 81, 81, 81, 81, 81, 81, 30, 31, 81, 81, 32, 32, 33, 32, 33, 32, 33, 32, 33, 32, 33, 32, 33, 32, 33, 32, 33, 32, 33, 32, 33, 1, 1, 1, 1, 1, 1, 1, 1, 1, 1, 1, 1, 1, 1, 1, 1, 1, 1, 1, 32],
         "height":18,
         "name":"Tile Layer 1",
         "opacity":1,
         "type":"tilelayer",
         "visible":true,
         "width":20,
         "x":0,
         "y":0
        }, 
        {
         "height":18,
         "name":"Object Layer 1",
         "objects":[
                {
                 "height":32,
                 "name":"Ladder",
                 "properties":
                    {

                    },
                 "type":"Ladder",
                 "visible":true,
                 "width":16,
                 "x":120,
                 "y":96
                }, 
                {
                 "height":32,
                 "name":"Ladder",
                 "properties":
                    {

                    },
                 "type":"Ladder",
                 "visible":true,
                 "width":16,
                 "x":88,
                 "y":64
                }, 
                {
                 "height":32,
                 "name":"Ladder",
                 "properties":
                    {

                    },
                 "type":"Ladder",
                 "visible":true,
                 "width":16,
                 "x":8,
                 "y":64
                }, 
                {
                 "height":16,
                 "name":"Fire",
                 "properties":
                    {

                    },
                 "type":"Fire",
                 "visible":true,
                 "width":16,
                 "x":16,
                 "y":112
                }, 
                {
                 "height":32,
                 "name":"Ladder",
                 "properties":
                    {

                    },
                 "type":"Ladder",
                 "visible":true,
                 "width":16,
                 "x":112,
                 "y":32
                }, 
                {
                 "height":16,
                 "name":"Bomb",
                 "properties":
                    {
                     "active":"0"
                    },
                 "type":"Bomb",
                 "visible":true,
                 "width":16,
                 "x":136,
                 "y":16
                }, 
                {
                 "height":32,
                 "name":"Ladder",
                 "properties":
                    {

                    },
                 "type":"Ladder",
                 "visible":true,
                 "width":16,
                 "x":40,
                 "y":96
                }, 
                {
                 "height":24,
                 "name":"Door",
                 "properties":
                    {

                    },
                 "type":"Door",
                 "visible":true,
                 "width":24,
                 "x":32,
                 "y":40
                }, 
                {
                 "height":16,
                 "name":"Cat",
                 "properties":
                    {

                    },
                 "type":"Cat",
                 "visible":true,
                 "width":16,
                 "x":8,
                 "y":48
                }, 
                {
                 "height":16,
                 "name":"Walker",
                 "properties":
                    {

                    },
                 "type":"",
                 "visible":true,
                 "width":16,
                 "x":112,
                 "y":16
                }, 
                {
                 "height":16,
                 "name":"Walker",
                 "properties":
                    {

                    },
                 "type":"",
                 "visible":true,
                 "width":16,
                 "x":64,
                 "y":112
                }],
         "opacity":1,
         "type":"objectgroup",
         "visible":false,
         "width":20,
         "x":0,
         "y":0
        }],
 "orientation":"orthogonal",
 "properties":
    {
     "time":"300"
    },
 "tileheight":8,
 "tilesets":[
        {
         "firstgid":1,
         "image":"tilesbasic.png",
         "imageheight":56,
         "imagewidth":160,
         "margin":0,
         "name":"basic",
         "properties":
            {

            },
         "spacing":0,
         "tileheight":8,
         "tilewidth":8,
         "transparentcolor":"#ff00ff"
        }],
 "tilewidth":8,
 "version":1,
 "width":20
}